tnthai/README.md
tnthai/__init__.py
tnthai/segment.py
tnthai/segmentDict.py
tnthai/segmentList.py
tnthai/swathclone/AbstractWordSegment.py
tnthai/swathclone/README.md
tnthai/swathclone/SC.py
tnthai/swathclone/SCDict.py
tnthai/swathclone/SCList.py
tnthai/swathclone/__init__.py
tnthai/swathclone/dict/my.trie
tnthai-1.7.data/scripts/tnthai-run
tnthai-1.7.data/scripts/tnthai-test
tnthai-1.7.dist-info/METADATA
tnthai-1.7.dist-info/RECORD
tnthai-1.7.dist-info/WHEEL
tnthai-1.7.dist-info/top_level.txt
