Metadata-Version: 2.1
Name: tnthai
Version: 1.7
Summary: tnthai for Python
Home-page: https://gitlab.thinknet.co.th/research/swathclone
Author: Supphawit
Author-email: supphawit@thinknet.co.th
License: Thinknet
Keywords: tnthai thinknet thai wordsegment
Platform: UNKNOWN
Requires-Dist: datrie
